qumin/__init__.py
qumin/calc_paradigm_entropy.py
qumin/cli.py
qumin/entropy_heatmap.py
qumin/find_macroclasses.py
qumin/find_patterns.py
qumin/make_lattice.py
qumin/microclass_heatmap.py
qumin/clustering/__init__.py
qumin/clustering/algorithms.py
qumin/clustering/descriptionlength.py
qumin/clustering/node.py
qumin/config/__init__.py
qumin/config/help.yaml
qumin/config/qumin.yaml
qumin/entropy/__init__.py
qumin/entropy/distribution.py
qumin/lattice/HighlightSubTrees.js
qumin/lattice/__init__.py
qumin/lattice/lattice.py
qumin/lattice/table.css
qumin/representations/__init__.py
qumin/representations/alignment.py
qumin/representations/contexts.py
qumin/representations/frequencies.py
qumin/representations/generalize.py
qumin/representations/paradigms.py
qumin/representations/patterns.py
qumin/representations/quantity.py
qumin/representations/segments.py
qumin/utils/__init__.py
qumin-3.0.21.dist-info/LICENCE
qumin-3.0.21.dist-info/METADATA
qumin-3.0.21.dist-info/WHEEL
qumin-3.0.21.dist-info/entry_points.txt
qumin-3.0.21.dist-info/top_level.txt
qumin-3.0.21.dist-info/RECORD
